lobo_rig/ESP32_C3/__init__.py
lobo_rig/ESP32_C3/pin.py
lobo_rig/ESP32_S3_mini/__init__.py
lobo_rig/ESP32_S3_mini/pin.py
lobo_rig/ESP32_S3_pro/__init__.py
lobo_rig/ESP32_S3_pro/pin.py
lobo_rig/RP2040/__init__.py
lobo_rig/RP2040/pin.py
lobo_rig/Raspberry_Pi_4/__init__.py
lobo_rig/Raspberry_Pi_4/pin.py
lobo_rig/__init__.py
lobo_rig/lobo_rig.py
lobo_rig/nRF52840/__init__.py
lobo_rig/nRF52840/pin.py
lobo_rig-0.4.6.dist-info/LICENSE
lobo_rig-0.4.6.dist-info/METADATA
lobo_rig-0.4.6.dist-info/WHEEL
lobo_rig-0.4.6.dist-info/RECORD
