Metadata-Version: 2.1
Name: lobo-rig
Version: 0.4.6
Summary: Pin variables for my controllers.
License: CC0 v1.0 Universal
Author: Lukasz Lobocki
Requires-Python: >=3.10,<4.0
Classifier: License :: Other/Proprietary License
Classifier: Programming Language :: Python :: 3
Classifier: Programming Language :: Python :: 3.10
Classifier: Programming Language :: Python :: 3.11
